hybkit/__about__.py
hybkit/__about__.pyc
hybkit/__init__.py
hybkit/__init__.pyc
hybkit/analysis.py
hybkit/analysis.pyc
hybkit/errors.py
hybkit/find_type_string_match.csv
hybkit/plot.py
hybkit/settings.py
hybkit/string_match_params.csv
hybkit/type_finder.py
hybkit/util.py
hybkit-0.3.6.data/data/hybkit-v0.3.6/.gitignore
hybkit-0.3.6.data/data/hybkit-v0.3.6/LICENSE
hybkit-0.3.6.data/data/hybkit-v0.3.6/README.rst
hybkit-0.3.6.data/data/hybkit-v0.3.6/requirements.txt
hybkit-0.3.6.data/data/hybkit-v0.3.6/setup.py
hybkit-0.3.6.data/data/hybkit-v0.3.6/docs/Makefile
hybkit-0.3.6.data/data/hybkit-v0.3.6/docs/conf.py
hybkit-0.3.6.data/data/hybkit-v0.3.6/docs/example_01_link.rst
hybkit-0.3.6.data/data/hybkit-v0.3.6/docs/example_02_link.rst
hybkit-0.3.6.data/data/hybkit-v0.3.6/docs/example_03_link.rst
hybkit-0.3.6.data/data/hybkit-v0.3.6/docs/example_04_link.rst
hybkit-0.3.6.data/data/hybkit-v0.3.6/docs/index.rst
hybkit-0.3.6.data/data/hybkit-v0.3.6/docs/index_suffix.rst
hybkit-0.3.6.data/data/hybkit-v0.3.6/docs/make.bat
hybkit-0.3.6.data/data/hybkit-v0.3.6/docs/requirements.txt
hybkit-0.3.6.data/data/hybkit-v0.3.6/docs/source/about.rst
hybkit-0.3.6.data/data/hybkit-v0.3.6/docs/source/example_analyses.rst
hybkit-0.3.6.data/data/hybkit-v0.3.6/docs/source/hybkit.analysis.rst
hybkit-0.3.6.data/data/hybkit-v0.3.6/docs/source/hybkit.errors.rst
hybkit-0.3.6.data/data/hybkit-v0.3.6/docs/source/hybkit.plot.rst
hybkit-0.3.6.data/data/hybkit-v0.3.6/docs/source/hybkit.rst
hybkit-0.3.6.data/data/hybkit-v0.3.6/docs/source/hybkit.settings.rst
hybkit-0.3.6.data/data/hybkit-v0.3.6/docs/source/hybkit.type_finder.rst
hybkit-0.3.6.data/data/hybkit-v0.3.6/docs/source/hybkit.util.rst
hybkit-0.3.6.data/data/hybkit-v0.3.6/docs/source/hybkit_api.rst
hybkit-0.3.6.data/data/hybkit-v0.3.6/docs/source/hybkit_toolkit.rst
hybkit-0.3.6.data/data/hybkit-v0.3.6/docs/source/specification.rst
hybkit-0.3.6.data/data/hybkit-v0.3.6/docs/source/toolkit/hyb_analyze.rst
hybkit-0.3.6.dist-info/LICENSE
hybkit-0.3.6.dist-info/METADATA
hybkit-0.3.6.dist-info/WHEEL
hybkit-0.3.6.dist-info/top_level.txt
hybkit-0.3.6.dist-info/RECORD
