Metadata-Version: 2.1
Name: hybkit
Version: 0.3.6
Summary: Toolkit for analysis of chimeric (hybrid) RNA sequence data.
Home-page: https://github.com/RenneLab/hybkit
Author: Daniel Stribling
Author-email: ds@ufl.edu
Project-URL: Download as TAR, https://github.com/RenneLab/hybkit/tarball/v0.3.6
Project-URL: Renne Lab Github, https://github.com/RenneLab
Project-URL: Renne Lab Mainpage, https://www.rennelab.com/
Project-URL: Travis Hyb Format Specification, https://www.sciencedirect.com/science/article/pii/S1046202313004180
Keywords: genetics,genomics,microRNAs,Ribonomics,Hyb,Hybrids,CLASH,qCLASH,CLEAR-CLIP,Chimeric e-CLIP
Classifier: Development Status :: 5 - Production/Stable
Classifier: Natural Language :: English
Classifier: Intended Audience :: Science/Research
Classifier: Intended Audience :: Developers
Classifier: Topic :: Scientific/Engineering
Classifier: Topic :: Scientific/Engineering :: Bio-Informatics
Classifier: Topic :: Software Development :: Libraries :: Python Modules
Classifier: Operating System :: OS Independent
Classifier: License :: OSI Approved :: GNU General Public License v3 or later (GPLv3+)
Classifier: Programming Language :: Python :: 3.8
Classifier: Programming Language :: Python :: 3.9
Classifier: Programming Language :: Python :: 3.10
Classifier: Programming Language :: Python :: 3.11
Requires-Python: >=3.8
License-File: LICENSE
Requires-Dist: matplotlib
Requires-Dist: biopython
